django_support_lite/__init__.py
django_support_lite/apps.py
django_support_lite/checks.py
django_support_lite/enums.py
django_support_lite/urls.py
django_support_lite/forms/fields/__init__.py
django_support_lite/forms/fields/multiple_file_field.py
django_support_lite/forms/inputs/__init__.py
django_support_lite/forms/inputs/multiple_file_input.py
django_support_lite/forms/validators/__init__.py
django_support_lite/forms/validators/file_content_validator.py
django_support_lite/helpers/__init__.py
django_support_lite/helpers/email.py
django_support_lite/helpers/pagination.py
django_support_lite/helpers/upload.py
django_support_lite/migrations/0001_initial.py
django_support_lite/migrations/__init__.py
django_support_lite/models/__init__.py
django_support_lite/models/image.py
django_support_lite/models/message.py
django_support_lite/models/ticket.py
django_support_lite/static/django_support_lite/favicon.ico
django_support_lite/static/django_support_lite/css/bootstrap.min.css
django_support_lite/templates/layout.html
django_support_lite/templates/emails/message_created.html
django_support_lite/templates/emails/message_created.txt
django_support_lite/templates/emails/ticket_created_accessor.html
django_support_lite/templates/emails/ticket_created_accessor.txt
django_support_lite/templates/emails/ticket_created_manager.html
django_support_lite/templates/emails/ticket_created_manager.txt
django_support_lite/templates/partials/form.html
django_support_lite/templates/partials/pagination.html
django_support_lite/templates/partials/stub.html
django_support_lite/templates/views/tickets/create.html
django_support_lite/templates/views/tickets/list.html
django_support_lite/templates/views/tickets/view.html
django_support_lite/templatetags/__init__.py
django_support_lite/templatetags/form.py
django_support_lite/templatetags/ticket.py
django_support_lite/views/__init__.py
django_support_lite/views/view.py
django_support_lite/views/forms/__init__.py
django_support_lite-0.2.10.dist-info/METADATA
django_support_lite-0.2.10.dist-info/WHEEL
django_support_lite-0.2.10.dist-info/top_level.txt
django_support_lite-0.2.10.dist-info/RECORD
