Metadata-Version: 2.1
Name: django-support-lite
Version: 0.2.10
Summary: Django Support Lite
Home-page: http://github.com/kn2gc3q/django_support_lite
Author: kn2gc3q
Author-email: kn2gc3q@gmail.com
License: MIT
Platform: UNKNOWN
